dallinger/__init__.py
dallinger/bots.py
dallinger/config.py
dallinger/constraints.py
dallinger/data.py
dallinger/db.py
dallinger/deployment.py
dallinger/experiment.py
dallinger/information.py
dallinger/jupyter.py
dallinger/logging.ini
dallinger/models.py
dallinger/mturk.py
dallinger/networks.py
dallinger/nodes.py
dallinger/notifications.py
dallinger/patches.py
dallinger/postgres_copy.py
dallinger/processes.py
dallinger/prolific.py
dallinger/pytest_dallinger.py
dallinger/recruiters.py
dallinger/redis_utils.py
dallinger/registration.py
dallinger/transformations.py
dallinger/utils.py
dallinger/version.py
dallinger/command_line/__init__.py
dallinger/command_line/config.py
dallinger/command_line/develop.py
dallinger/command_line/docker.py
dallinger/command_line/docker_ssh.py
dallinger/command_line/ec2.py
dallinger/command_line/prolific.py
dallinger/command_line/utils.py
dallinger/command_line/lib/__init__.py
dallinger/command_line/lib/ec2.py
dallinger/default_configs/.dallingerconfig
dallinger/default_configs/global_config_defaults.txt
dallinger/default_configs/local_config_defaults.txt
dallinger/dev_server/app.py
dallinger/dev_server/run.sh
dallinger/docker/__init__.py
dallinger/docker/deployment.py
dallinger/docker/prepare_docker_image.sh
dallinger/docker/tools.py
dallinger/docker/wheel_filename.py
dallinger/experiment_server/__init__.py
dallinger/experiment_server/dashboard.py
dallinger/experiment_server/experiment_server.py
dallinger/experiment_server/gunicorn.py
dallinger/experiment_server/replay.py
dallinger/experiment_server/sockets.py
dallinger/experiment_server/utils.py
dallinger/experiment_server/worker_events.py
dallinger/experiments/__init__.py
dallinger/frontend/static/robots.txt
dallinger/frontend/static/css/bootstrap.min.css
dallinger/frontend/static/css/dallinger.css
dallinger/frontend/static/css/dashboard.css
dallinger/frontend/static/images/favicon.ico
dallinger/frontend/static/scripts/bootstrap.min.js
dallinger/frontend/static/scripts/clipboard.min.js
dallinger-12.1.0.dist-info/METADATA
dallinger-12.1.0.dist-info/WHEEL
dallinger-12.1.0.dist-info/entry_points.txt
dallinger-12.1.0.dist-info/licenses/LICENSE
dallinger-12.1.0.dist-info/RECORD
