Metadata-Version: 2.4
Name: dallinger
Version: 12.1.0
Summary: Laboratory automation for the behavioral and social sciences
Project-URL: Changelog, https://github.com/Dallinger/Dallinger/blob/master/CHANGELOG.md
Project-URL: Documentation, https://dallinger.readthedocs.io
Project-URL: Homepage, https://github.com/Dallinger/Dallinger
Project-URL: Issues, http://github.com/Dallinger/Dallinger/issues
Project-URL: Repository, https://github.com/Dallinger/Dallinger
Maintainer-email: Jordan Suchow <jws@stevens.edu>, Peter Harrison <pmch2@cam.ac.uk>, Frank Höger <frank.hoeger@ae.mpg.de>
License: The MIT License (MIT)
License-File: LICENSE
Keywords: cultural evolution,experiments,psychology,science
Classifier: Development Status :: 4 - Beta
Classifier: Framework :: Flask
Classifier: Intended Audience :: Science/Research
Classifier: License :: OSI Approved :: MIT License
Classifier: Operating System :: OS Independent
Classifier: Programming Language :: Python :: 3.10
Classifier: Programming Language :: Python :: 3.11
Classifier: Programming Language :: Python :: 3.12
Classifier: Programming Language :: Python :: 3.13
Classifier: Topic :: Scientific/Engineering
Requires-Python: >=3.10
Requires-Dist: ansi2html
Requires-Dist: apscheduler
Requires-Dist: beautifulsoup4
Requires-Dist: boto3
Requires-Dist: build
Requires-Dist: cached-property
Requires-Dist: click
Requires-Dist: faker
Requires-Dist: flask
Requires-Dist: flask-crossdomain
Requires-Dist: flask-login
Requires-Dist: flask-sock
Requires-Dist: flask-wtf
Requires-Dist: gevent
Requires-Dist: gunicorn[gevent]
Requires-Dist: heroku3
Requires-Dist: ipython<9
Requires-Dist: numpy<2.3
Requires-Dist: paramiko<4.0.0
Requires-Dist: pexpect
Requires-Dist: pip-tools
Requires-Dist: platformdirs
Requires-Dist: psutil
Requires-Dist: psycopg2
Requires-Dist: pygtail
Requires-Dist: pyopenssl
Requires-Dist: python-json-logger
Requires-Dist: redis
Requires-Dist: requests
Requires-Dist: rq
Requires-Dist: selenium
Requires-Dist: sqlalchemy<2
Requires-Dist: tabulate
Requires-Dist: tenacity
Requires-Dist: timeago
Requires-Dist: tzlocal
Requires-Dist: ua-parser
Requires-Dist: urllib3
Requires-Dist: user-agents
Requires-Dist: uv
Requires-Dist: yaspin
Provides-Extra: data
Requires-Dist: pandas; extra == 'data'
Requires-Dist: tablib[all]; extra == 'data'
Provides-Extra: dev
Requires-Dist: alabaster; extra == 'dev'
Requires-Dist: black; extra == 'dev'
Requires-Dist: black[jupyter]; extra == 'dev'
Requires-Dist: bump2version; extra == 'dev'
Requires-Dist: coverage; extra == 'dev'
Requires-Dist: coverage-pth; extra == 'dev'
Requires-Dist: flake8; extra == 'dev'
Requires-Dist: isort; extra == 'dev'
Requires-Dist: myst-parser; extra == 'dev'
Requires-Dist: pre-commit; extra == 'dev'
Requires-Dist: pycodestyle; extra == 'dev'
Requires-Dist: pypandoc; extra == 'dev'
Requires-Dist: pytest; extra == 'dev'
Requires-Dist: pytest-rerunfailures; extra == 'dev'
Requires-Dist: sphinx-js; extra == 'dev'
Requires-Dist: sphinx-rtd-theme; extra == 'dev'
Requires-Dist: sphinx<8.2; extra == 'dev'
Requires-Dist: sphinxcontrib-spelling; extra == 'dev'
Requires-Dist: tox; extra == 'dev'
Provides-Extra: docker
Requires-Dist: docker; extra == 'docker'
Requires-Dist: paramiko; extra == 'docker'
Requires-Dist: sshtunnel; extra == 'docker'
Provides-Extra: ec2
Requires-Dist: pandas; extra == 'ec2'
Requires-Dist: paramiko; extra == 'ec2'
Requires-Dist: tqdm; extra == 'ec2'
Requires-Dist: yaspin; extra == 'ec2'
Provides-Extra: jupyter
Requires-Dist: ipywidgets; extra == 'jupyter'
Requires-Dist: jupyter; extra == 'jupyter'
Requires-Dist: jupyter-server; extra == 'jupyter'
